python_encrypt_code/__init__.py
python_encrypt_code/__main__.py
python_encrypt_code/data_zipper/__init__.py
python_encrypt_code/data_zipper/data_zipper.py
python_encrypt_code/data_zipper/data_zipper_interface.py
python_encrypt_code/file_encrypter/__init__.py
python_encrypt_code/file_encrypter/file_encrypter.py
python_encrypt_code/file_encrypter/file_encrypter_interface.py
python_encrypt_code/module_importer/__init__.py
python_encrypt_code/module_importer/module_importer.py
python_encrypt_code/module_importer/module_importer_interface.py
python_encrypt_code/password_provider/__init__.py
python_encrypt_code/password_provider/password_provider.py
python_encrypt_code/password_provider/password_provider_interface.py
python_encrypt_code/utils/__init__.py
python_encrypt_code/utils/decrypt_to_disk.py
python_encrypt_code/utils/encrypt_folder.py
python_encrypt_code/utils/generate_password.py
python_encrypt_code-0.1.1.dist-info/METADATA
python_encrypt_code-0.1.1.dist-info/WHEEL
python_encrypt_code-0.1.1.dist-info/entry_points.txt
python_encrypt_code-0.1.1.dist-info/licenses/LICENSE
python_encrypt_code-0.1.1.dist-info/RECORD
