Metadata-Version: 2.4
Name: python-encrypt-code
Version: 0.1.1
Summary: Python-based command line tool to encrypt and decrypt Python modules.
Project-URL: source, https://gitea.gt-proj.com/brian/python-encrypt-code
Author-email: Brian Bjarke Jensen <schnitzelen@gmail.com>
License-Expression: MIT
License-File: LICENSE
Classifier: Operating System :: OS Independent
Classifier: Programming Language :: Python :: 3
Requires-Python: >=3.12
Requires-Dist: cryptography>=46.0.3
